{
  "animateLoading": true,
  "borderColor": "#E0DEDE",
  "borderWidth": "1",
  "bottomRow": 10,
  "canFreezeColumn": true,
  "columnOrder": [
    "id",
    "gender",
    "latitude",
    "longitude",
    "dob",
    "phone",
    "email",
    "image",
    "country",
    "name",
    "created_at",
    "updated_at"
  ],
  "columnUpdatedAt": 1715265168634,
  "columnWidthMap": {},
  "defaultPageSize": 0,
  "defaultSelectedRowIndex": 0,
  "defaultSelectedRowIndices": [
    0
  ],
  "delimiter": ",",
  "displayName": "Table",
  "dynamicBindingPathList": [
    {
      "key": "tableData"
    },
    {
      "key": "primaryColumns.id.computedValue"
    },
    {
      "key": "primaryColumns.gender.computedValue"
    },
    {
      "key": "primaryColumns.latitude.computedValue"
    },
    {
      "key": "primaryColumns.longitude.computedValue"
    },
    {
      "key": "primaryColumns.dob.computedValue"
    },
    {
      "key": "primaryColumns.phone.computedValue"
    },
    {
      "key": "primaryColumns.email.computedValue"
    },
    {
      "key": "primaryColumns.image.computedValue"
    },
    {
      "key": "primaryColumns.country.computedValue"
    },
    {
      "key": "primaryColumns.name.computedValue"
    },
    {
      "key": "primaryColumns.created_at.computedValue"
    },
    {
      "key": "primaryColumns.updated_at.computedValue"
    }
  ],
  "dynamicPropertyPathList": [],
  "dynamicTriggerPathList": [],
  "enableClientSideSearch": true,
  "hideCard": false,
  "horizontalAlignment": "LEFT",
  "inlineEditingSaveOption": "ROW_LEVEL",
  "isDeprecated": false,
  "isLoading": false,
  "isSortable": true,
  "isVisible": true,
  "isVisibleDownload": true,
  "isVisibleFilters": true,
  "isVisiblePagination": true,
  "isVisibleSearch": true,
  "key": "td7r67dv6g",
  "label": "Data",
  "leftColumn": 0,
  "mobileBottomRow": 10,
  "mobileLeftColumn": 0,
  "mobileRightColumn": 64,
  "mobileTopRow": 0,
  "needsErrorInfo": false,
  "needsHeightForContent": true,
  "onCanvasUI": {
    "disableParentSelection": false,
    "focusBGCSSVar": "--on-canvas-ui-widget-focus",
    "focusColorCSSVar": "--on-canvas-ui-widget-selection",
    "selectionBGCSSVar": "--on-canvas-ui-widget-selection",
    "selectionColorCSSVar": "--on-canvas-ui-widget-focus"
  },
  "pageSize": 8,
  "parentColumnSpace": 1,
  "parentId": "2ygyhqk7xr",
  "parentRowSpace": 10,
  "primaryColumns": {
    "country": {
      "alias": "country",
      "allowCellWrapping": false,
      "allowSameOptionsInNewRow": true,
      "cellBackground": "",
      "columnType": "text",
      "computedValue": "{{Table2CopyCopy.processedTableData.map((currentRow, currentIndex) => ( currentRow[\"country\"]))}}",
      "currencyCode": "USD",
      "decimals": 0,
      "enableFilter": true,
      "enableSort": true,
      "fontStyle": "",
      "horizontalAlignment": "LEFT",
      "id": "country",
      "index": 8,
      "isCellEditable": false,
      "isCellVisible": true,
      "isDerived": false,
      "isDisabled": false,
      "isDiscardVisible": true,
      "isEditable": false,
      "isSaveVisible": true,
      "isVisible": true,
      "label": "country",
      "notation": "standard",
      "originalId": "country",
      "sticky": "",
      "textColor": "",
      "textSize": "0.875rem",
      "thousandSeparator": true,
      "validation": {},
      "verticalAlignment": "CENTER",
      "width": 150
    },
    "created_at": {
      "alias": "created_at",
      "allowCellWrapping": false,
      "allowSameOptionsInNewRow": true,
      "cellBackground": "",
      "columnType": "text",
      "computedValue": "{{Table2CopyCopy.processedTableData.map((currentRow, currentIndex) => ( currentRow[\"created_at\"]))}}",
      "currencyCode": "USD",
      "decimals": 0,
      "enableFilter": true,
      "enableSort": true,
      "fontStyle": "",
      "horizontalAlignment": "LEFT",
      "id": "created_at",
      "index": 10,
      "isCellEditable": false,
      "isCellVisible": true,
      "isDerived": false,
      "isDisabled": false,
      "isDiscardVisible": true,
      "isEditable": false,
      "isSaveVisible": true,
      "isVisible": true,
      "label": "created_at",
      "notation": "standard",
      "originalId": "created_at",
      "sticky": "",
      "textColor": "",
      "textSize": "0.875rem",
      "thousandSeparator": true,
      "validation": {},
      "verticalAlignment": "CENTER",
      "width": 150
    },
    "dob": {
      "alias": "dob",
      "allowCellWrapping": false,
      "allowSameOptionsInNewRow": true,
      "cellBackground": "",
      "columnType": "date",
      "computedValue": "{{Table2CopyCopy.processedTableData.map((currentRow, currentIndex) => ( currentRow[\"dob\"]))}}",
      "currencyCode": "USD",
      "decimals": 0,
      "enableFilter": true,
      "enableSort": true,
      "fontStyle": "",
      "horizontalAlignment": "LEFT",
      "id": "dob",
      "index": 4,
      "isCellEditable": false,
      "isCellVisible": true,
      "isDerived": false,
      "isDisabled": false,
      "isDiscardVisible": true,
      "isEditable": false,
      "isSaveVisible": true,
      "isVisible": true,
      "label": "dob",
      "notation": "standard",
      "originalId": "dob",
      "sticky": "",
      "textColor": "",
      "textSize": "0.875rem",
      "thousandSeparator": true,
      "validation": {},
      "verticalAlignment": "CENTER",
      "width": 150
    },
    "email": {
      "alias": "email",
      "allowCellWrapping": false,
      "allowSameOptionsInNewRow": true,
      "cellBackground": "",
      "columnType": "text",
      "computedValue": "{{Table2CopyCopy.processedTableData.map((currentRow, currentIndex) => ( currentRow[\"email\"]))}}",
      "currencyCode": "USD",
      "decimals": 0,
      "enableFilter": true,
      "enableSort": true,
      "fontStyle": "",
      "horizontalAlignment": "LEFT",
      "id": "email",
      "index": 6,
      "isCellEditable": false,
      "isCellVisible": true,
      "isDerived": false,
      "isDisabled": false,
      "isDiscardVisible": true,
      "isEditable": false,
      "isSaveVisible": true,
      "isVisible": true,
      "label": "email",
      "notation": "standard",
      "originalId": "email",
      "sticky": "",
      "textColor": "",
      "textSize": "0.875rem",
      "thousandSeparator": true,
      "validation": {},
      "verticalAlignment": "CENTER",
      "width": 150
    },
    "gender": {
      "alias": "gender",
      "allowCellWrapping": false,
      "allowSameOptionsInNewRow": true,
      "cellBackground": "",
      "columnType": "text",
      "computedValue": "{{Table2CopyCopy.processedTableData.map((currentRow, currentIndex) => ( currentRow[\"gender\"]))}}",
      "currencyCode": "USD",
      "decimals": 0,
      "enableFilter": true,
      "enableSort": true,
      "fontStyle": "",
      "horizontalAlignment": "LEFT",
      "id": "gender",
      "index": 1,
      "isCellEditable": false,
      "isCellVisible": true,
      "isDerived": false,
      "isDisabled": false,
      "isDiscardVisible": true,
      "isEditable": false,
      "isSaveVisible": true,
      "isVisible": true,
      "label": "gender",
      "notation": "standard",
      "originalId": "gender",
      "sticky": "",
      "textColor": "",
      "textSize": "0.875rem",
      "thousandSeparator": true,
      "validation": {},
      "verticalAlignment": "CENTER",
      "width": 150
    },
    "id": {
      "alias": "id",
      "allowCellWrapping": false,
      "allowSameOptionsInNewRow": true,
      "cellBackground": "",
      "columnType": "number",
      "computedValue": "{{Table2CopyCopy.processedTableData.map((currentRow, currentIndex) => ( currentRow[\"id\"]))}}",
      "currencyCode": "USD",
      "decimals": 0,
      "enableFilter": true,
      "enableSort": true,
      "fontStyle": "",
      "horizontalAlignment": "LEFT",
      "id": "id",
      "index": 0,
      "isCellEditable": false,
      "isCellVisible": true,
      "isDerived": false,
      "isDisabled": false,
      "isDiscardVisible": true,
      "isEditable": false,
      "isSaveVisible": true,
      "isVisible": true,
      "label": "id",
      "notation": "standard",
      "originalId": "id",
      "sticky": "",
      "textColor": "",
      "textSize": "0.875rem",
      "thousandSeparator": true,
      "validation": {},
      "verticalAlignment": "CENTER",
      "width": 150
    },
    "image": {
      "alias": "image",
      "allowCellWrapping": false,
      "allowSameOptionsInNewRow": true,
      "cellBackground": "",
      "columnType": "text",
      "computedValue": "{{Table2CopyCopy.processedTableData.map((currentRow, currentIndex) => ( currentRow[\"image\"]))}}",
      "currencyCode": "USD",
      "decimals": 0,
      "enableFilter": true,
      "enableSort": true,
      "fontStyle": "",
      "horizontalAlignment": "LEFT",
      "id": "image",
      "index": 7,
      "isCellEditable": false,
      "isCellVisible": true,
      "isDerived": false,
      "isDisabled": false,
      "isDiscardVisible": true,
      "isEditable": false,
      "isSaveVisible": true,
      "isVisible": true,
      "label": "image",
      "notation": "standard",
      "originalId": "image",
      "sticky": "",
      "textColor": "",
      "textSize": "0.875rem",
      "thousandSeparator": true,
      "validation": {},
      "verticalAlignment": "CENTER",
      "width": 150
    },
    "latitude": {
      "alias": "latitude",
      "allowCellWrapping": false,
      "allowSameOptionsInNewRow": true,
      "cellBackground": "",
      "columnType": "text",
      "computedValue": "{{Table2CopyCopy.processedTableData.map((currentRow, currentIndex) => ( currentRow[\"latitude\"]))}}",
      "currencyCode": "USD",
      "decimals": 0,
      "enableFilter": true,
      "enableSort": true,
      "fontStyle": "",
      "horizontalAlignment": "LEFT",
      "id": "latitude",
      "index": 2,
      "isCellEditable": false,
      "isCellVisible": true,
      "isDerived": false,
      "isDisabled": false,
      "isDiscardVisible": true,
      "isEditable": false,
      "isSaveVisible": true,
      "isVisible": true,
      "label": "latitude",
      "notation": "standard",
      "originalId": "latitude",
      "sticky": "",
      "textColor": "",
      "textSize": "0.875rem",
      "thousandSeparator": true,
      "validation": {},
      "verticalAlignment": "CENTER",
      "width": 150
    },
    "longitude": {
      "alias": "longitude",
      "allowCellWrapping": false,
      "allowSameOptionsInNewRow": true,
      "cellBackground": "",
      "columnType": "text",
      "computedValue": "{{Table2CopyCopy.processedTableData.map((currentRow, currentIndex) => ( currentRow[\"longitude\"]))}}",
      "currencyCode": "USD",
      "decimals": 0,
      "enableFilter": true,
      "enableSort": true,
      "fontStyle": "",
      "horizontalAlignment": "LEFT",
      "id": "longitude",
      "index": 3,
      "isCellEditable": false,
      "isCellVisible": true,
      "isDerived": false,
      "isDisabled": false,
      "isDiscardVisible": true,
      "isEditable": false,
      "isSaveVisible": true,
      "isVisible": true,
      "label": "longitude",
      "notation": "standard",
      "originalId": "longitude",
      "sticky": "",
      "textColor": "",
      "textSize": "0.875rem",
      "thousandSeparator": true,
      "validation": {},
      "verticalAlignment": "CENTER",
      "width": 150
    },
    "name": {
      "alias": "name",
      "allowCellWrapping": false,
      "allowSameOptionsInNewRow": true,
      "cellBackground": "",
      "columnType": "text",
      "computedValue": "{{Table2CopyCopy.processedTableData.map((currentRow, currentIndex) => ( currentRow[\"name\"]))}}",
      "currencyCode": "USD",
      "decimals": 0,
      "enableFilter": true,
      "enableSort": true,
      "fontStyle": "",
      "horizontalAlignment": "LEFT",
      "id": "name",
      "index": 9,
      "isCellEditable": false,
      "isCellVisible": true,
      "isDerived": false,
      "isDisabled": false,
      "isDiscardVisible": true,
      "isEditable": false,
      "isSaveVisible": true,
      "isVisible": true,
      "label": "name",
      "notation": "standard",
      "originalId": "name",
      "sticky": "",
      "textColor": "",
      "textSize": "0.875rem",
      "thousandSeparator": true,
      "validation": {},
      "verticalAlignment": "CENTER",
      "width": 150
    },
    "phone": {
      "alias": "phone",
      "allowCellWrapping": false,
      "allowSameOptionsInNewRow": true,
      "cellBackground": "",
      "columnType": "text",
      "computedValue": "{{Table2CopyCopy.processedTableData.map((currentRow, currentIndex) => ( currentRow[\"phone\"]))}}",
      "currencyCode": "USD",
      "decimals": 0,
      "enableFilter": true,
      "enableSort": true,
      "fontStyle": "",
      "horizontalAlignment": "LEFT",
      "id": "phone",
      "index": 5,
      "isCellEditable": false,
      "isCellVisible": true,
      "isDerived": false,
      "isDisabled": false,
      "isDiscardVisible": true,
      "isEditable": false,
      "isSaveVisible": true,
      "isVisible": true,
      "label": "phone",
      "notation": "standard",
      "originalId": "phone",
      "sticky": "",
      "textColor": "",
      "textSize": "0.875rem",
      "thousandSeparator": true,
      "validation": {},
      "verticalAlignment": "CENTER",
      "width": 150
    },
    "updated_at": {
      "alias": "updated_at",
      "allowCellWrapping": false,
      "allowSameOptionsInNewRow": true,
      "cellBackground": "",
      "columnType": "text",
      "computedValue": "{{Table2CopyCopy.processedTableData.map((currentRow, currentIndex) => ( currentRow[\"updated_at\"]))}}",
      "currencyCode": "USD",
      "decimals": 0,
      "enableFilter": true,
      "enableSort": true,
      "fontStyle": "",
      "horizontalAlignment": "LEFT",
      "id": "updated_at",
      "index": 11,
      "isCellEditable": false,
      "isCellVisible": true,
      "isDerived": false,
      "isDisabled": false,
      "isDiscardVisible": true,
      "isEditable": false,
      "isSaveVisible": true,
      "isVisible": true,
      "label": "updated_at",
      "notation": "standard",
      "originalId": "updated_at",
      "sticky": "",
      "textColor": "",
      "textSize": "0.875rem",
      "thousandSeparator": true,
      "validation": {},
      "verticalAlignment": "CENTER",
      "width": 150
    }
  },
  "renderMode": "CANVAS",
  "responsiveBehavior": "fill",
  "rightColumn": 64,
  "searchKey": "",
  "tableData": "{{Select_public_users1.data}}",
  "tags": [
    "Suggested",
    "Display"
  ],
  "textSize": "0.875rem",
  "topRow": 0,
  "totalRecordsCount": 0,
  "type": "WDS_TABLE_WIDGET",
  "version": 2,
  "verticalAlignment": "CENTER",
  "widgetId": "u4ocm8g086",
  "widgetName": "Table2CopyCopy"
}