{
  "animateLoading": true,
  "bottomRow": 10,
  "buttonColor": "accent",
  "buttonLabel": "Action",
  "buttonVariant": "filled",
  "canFreezeColumn": true,
  "columnOrder": [],
  "columnUpdatedAt": 1716801382490,
  "columnWidthMap": {},
  "defaultPageSize": 0,
  "defaultSelectedRowIndex": 0,
  "defaultSelectedRowIndices": [
    0
  ],
  "delimiter": ",",
  "displayName": "Table",
  "dynamicBindingPathList": [],
  "dynamicPropertyPathList": [],
  "dynamicTriggerPathList": [],
  "enableClientSideSearch": true,
  "hideCard": false,
  "horizontalAlignment": "start",
  "inlineEditingSaveOption": "ROW_LEVEL",
  "isDeprecated": false,
  "isLoading": false,
  "isSortable": true,
  "isVisible": true,
  "isVisibleDownload": true,
  "isVisibleFilters": true,
  "isVisiblePagination": false,
  "isVisibleSearch": false,
  "key": "vx08gkapgl",
  "label": "Data",
  "leftColumn": 0,
  "mobileBottomRow": 10,
  "mobileLeftColumn": 0,
  "mobileRightColumn": 64,
  "mobileTopRow": 0,
  "needsErrorInfo": false,
  "needsHeightForContent": true,
  "onCanvasUI": {
    "disableParentSelection": false,
    "focusBGCSSVar": "--on-canvas-ui-widget-focus",
    "focusColorCSSVar": "--on-canvas-ui-widget-selection",
    "selectionBGCSSVar": "--on-canvas-ui-widget-selection",
    "selectionColorCSSVar": "--on-canvas-ui-widget-focus"
  },
  "pageSize": "4",
  "parentColumnSpace": 1,
  "parentId": "bvn3un2ohf",
  "parentRowSpace": 10,
  "primaryColumns": {},
  "renderMode": "CANVAS",
  "responsiveBehavior": "fill",
  "rightColumn": 64,
  "searchKey": "",
  "tableData": "",
  "tags": [
    "Suggested",
    "Display"
  ],
  "topRow": 0,
  "totalRecordsCount": 0,
  "type": "WDS_TABLE_WIDGET",
  "version": 2,
  "verticalAlignment": "center",
  "widgetId": "9q47az5zb5",
  "widgetName": "Table5"
}